tryppy/__init__.py
tryppy/evaluation.py
tryppy/feature_visualizer.py
tryppy/file_handler.py
tryppy/tryppy.py
tryppy/resources/default_config.json
tryppy/resources/rf_model/label_encoder.joblib
tryppy/resources/rf_model/random_forest_model.joblib
tryppy/transformations/__init__.py
tryppy/transformations/classification.py
tryppy/transformations/feature_extraction.py
tryppy/transformations/instance_segmentation.py
tryppy/transformations/model.py
tryppy/transformations/segmentation.py
tryppy-0.1.0.dist-info/LICENSE
tryppy-0.1.0.dist-info/METADATA
tryppy-0.1.0.dist-info/WHEEL
tryppy-0.1.0.dist-info/top_level.txt
tryppy-0.1.0.dist-info/RECORD
