Metadata-Version: 2.1
Name: tryppy
Version: 0.1.0
Summary: Kurze Beschreibung deines Pakets
Home-page: https://github.com/himmiE/tryppy
Author: Emely Himmstedt
License: MIT
Classifier: Programming Language :: Python :: 3
Classifier: Operating System :: OS Independent
Requires-Python: >=3.6
License-File: LICENSE
Requires-Dist: numpy
Requires-Dist: scipy
Requires-Dist: scikit-image
Requires-Dist: scikit-learn
Requires-Dist: opencv-python
Requires-Dist: spatial-efd
Requires-Dist: tensorflow
Requires-Dist: keras
Requires-Dist: matplotlib
Requires-Dist: shapely
Requires-Dist: joblib
Requires-Dist: networkx
Requires-Dist: pandas
Requires-Dist: rasterio
Requires-Dist: tqdm
Requires-Dist: tifffile
Requires-Dist: setuptools
Provides-Extra: dev
Requires-Dist: twine >=4.0.2 ; extra == 'dev'
